odoo/addons/users_ldap_mail/README.rst
odoo/addons/users_ldap_mail/__init__.py
odoo/addons/users_ldap_mail/__manifest__.py
odoo/addons/users_ldap_mail/i18n/de.po
odoo/addons/users_ldap_mail/i18n/es.po
odoo/addons/users_ldap_mail/i18n/fr.po
odoo/addons/users_ldap_mail/i18n/hr.po
odoo/addons/users_ldap_mail/i18n/hr_HR.po
odoo/addons/users_ldap_mail/i18n/pt_BR.po
odoo/addons/users_ldap_mail/i18n/sl.po
odoo/addons/users_ldap_mail/i18n/users_ldap_mail.pot
odoo/addons/users_ldap_mail/i18n/zh_CN.po
odoo/addons/users_ldap_mail/models/__init__.py
odoo/addons/users_ldap_mail/models/users_ldap_model.py
odoo/addons/users_ldap_mail/readme/CONTRIBUTORS.rst
odoo/addons/users_ldap_mail/readme/DESCRIPTION.rst
odoo/addons/users_ldap_mail/readme/USAGE.rst
odoo/addons/users_ldap_mail/static/description/icon.png
odoo/addons/users_ldap_mail/static/description/index.html
odoo/addons/users_ldap_mail/views/res_company_ldap.xml
odoo12_addon_users_ldap_mail-12.0.1.0.1.dist-info/METADATA
odoo12_addon_users_ldap_mail-12.0.1.0.1.dist-info/WHEEL
odoo12_addon_users_ldap_mail-12.0.1.0.1.dist-info/top_level.txt
odoo12_addon_users_ldap_mail-12.0.1.0.1.dist-info/RECORD
